genkit/py.typed
genkit/plugins/google_genai/__init__.py
genkit/plugins/google_genai/constants.py
genkit/plugins/google_genai/google.py
genkit/plugins/google_genai/models/__init__.py
genkit/plugins/google_genai/models/embedder.py
genkit/plugins/google_genai/models/gemini.py
genkit/plugins/google_genai/models/imagen.py
genkit/plugins/google_genai/models/utils.py
genkit/plugins/google_genai/models/context_caching/__init__.py
genkit/plugins/google_genai/models/context_caching/constants.py
genkit/plugins/google_genai/models/context_caching/types.py
genkit/plugins/google_genai/models/context_caching/utils.py
genkit/plugins/google_genai/__init__.py
genkit/plugins/google_genai/constants.py
genkit/plugins/google_genai/google.py
genkit/plugins/google_genai/models/__init__.py
genkit/plugins/google_genai/models/embedder.py
genkit/plugins/google_genai/models/gemini.py
genkit/plugins/google_genai/models/imagen.py
genkit/plugins/google_genai/models/utils.py
genkit/plugins/google_genai/models/context_caching/__init__.py
genkit/plugins/google_genai/models/context_caching/constants.py
genkit/plugins/google_genai/models/context_caching/types.py
genkit/plugins/google_genai/models/context_caching/utils.py
genkit_plugin_google_genai-0.3.2.dist-info/METADATA
genkit_plugin_google_genai-0.3.2.dist-info/WHEEL
genkit_plugin_google_genai-0.3.2.dist-info/licenses/LICENSE
genkit_plugin_google_genai-0.3.2.dist-info/RECORD
